miyuki/__init__.py
miyuki/config.py
miyuki/ffmpeg_processor.py
miyuki/logger.py
miyuki/main.py
miyuki/url_sources.py
miyuki/utils.py
miyuki/video_downloader.py
miyuki-0.8.1.dist-info/licenses/LICENSE
miyuki-0.8.1.dist-info/METADATA
miyuki-0.8.1.dist-info/WHEEL
miyuki-0.8.1.dist-info/entry_points.txt
miyuki-0.8.1.dist-info/top_level.txt
miyuki-0.8.1.dist-info/RECORD
