Metadata-Version: 2.4
Name: miyuki
Version: 0.8.1
Summary: Revived tool for downloading videos from MissAV website, with Cloudflare support.
Author-email: notmiyukisasaki <anon@example.com>
License: # Original work Copyright (c) [Original Author MiyukiQAQ - 2025]
Project-URL: Homepage, https://github.com/notmiyukisasaki/Miyuki-Reborn
Project-URL: Issues, https://github.com/notmiyukisasaki/Miyuki-Reborn/issues
Keywords: missav,downloader,video,cloudscraper,archive
Classifier: Development Status :: 4 - Beta
Classifier: Environment :: Console
Classifier: Intended Audience :: End Users/Desktop
Classifier: License :: OSI Approved :: MIT License
Classifier: Operating System :: OS Independent
Classifier: Programming Language :: Python :: 3
Classifier: Programming Language :: Python :: 3.8
Classifier: Programming Language :: Python :: 3.9
Classifier: Programming Language :: Python :: 3.10
Classifier: Programming Language :: Python :: 3.11
Classifier: Programming Language :: Python :: 3.12
Classifier: Topic :: Internet :: WWW/HTTP
Classifier: Topic :: Multimedia :: Video :: Capture
Classifier: Topic :: Utilities
Requires-Python: >=3.8
License-File: LICENSE
Requires-Dist: cloudscraper
Requires-Dist: curl_cffi
Dynamic: license-file
